odoo8_addon_connector-8.0.3.4.0-nspkg.pth
odoo_addons/connector/AUTHORS
odoo_addons/connector/CHANGES.rst
odoo_addons/connector/README.rst
odoo_addons/connector/__init__.py
odoo_addons/connector/__openerp__.py
odoo_addons/connector/backend.py
odoo_addons/connector/backend_model.py
odoo_addons/connector/connector.py
odoo_addons/connector/connector_menu.xml
odoo_addons/connector/deprecate.py
odoo_addons/connector/event.py
odoo_addons/connector/exception.py
odoo_addons/connector/openerp-connector-worker
odoo_addons/connector/producer.py
odoo_addons/connector/related_action.py
odoo_addons/connector/res_partner_view.xml
odoo_addons/connector/session.py
odoo_addons/connector/setting.py
odoo_addons/connector/setting_view.xml
odoo_addons/connector/checkpoint/__init__.py
odoo_addons/connector/checkpoint/checkpoint.py
odoo_addons/connector/checkpoint/checkpoint_view.xml
odoo_addons/connector/controllers/__init__.py
odoo_addons/connector/controllers/main.py
odoo_addons/connector/doc/Makefile
odoo_addons/connector/doc/bazaar
odoo_addons/connector/doc/conf.py
odoo_addons/connector/doc/index.rst
odoo_addons/connector/doc/make.bat
odoo_addons/connector/doc/_static/09_datamodel.png
odoo_addons/connector/doc/_static/connector_style.css
odoo_addons/connector/doc/_static/img/LogicSupply_Orange_260x80_transparent.png
odoo_addons/connector/doc/_static/img/akretion_logo.png
odoo_addons/connector/doc/_static/img/c2c_square_baseline_192.jpg
odoo_addons/connector/doc/_static/img/logo-debonix.jpg
odoo_addons/connector/doc/_static/img/magentoerpconnect.png
odoo_addons/connector/doc/_static/img/magentoerpconnect150.png
odoo_addons/connector/doc/_static/img/prestashoperpconnect.png
odoo_addons/connector/doc/_static/img/prestashoperpconnect150.png
odoo_addons/connector/doc/_templates/layout.html
odoo_addons/connector/doc/_templates/navbar.html
odoo_addons/connector/doc/_themes/.gitignore
odoo_addons/connector/doc/api/api_backend.rst
odoo_addons/connector/doc/api/api_backend_adapter.rst
odoo8_addon_connector-8.0.3.4.0.dist-info/METADATA
odoo8_addon_connector-8.0.3.4.0.dist-info/WHEEL
odoo8_addon_connector-8.0.3.4.0.dist-info/namespace_packages.txt
odoo8_addon_connector-8.0.3.4.0.dist-info/top_level.txt
odoo8_addon_connector-8.0.3.4.0.dist-info/RECORD
