Metadata-Version: 2.1
Name: odoo8-addon-connector
Version: 8.0.3.4.0
Summary: Connector
Home-page: http://odoo-connector.com
Author: Camptocamp,Openerp Connector Core Editors,Odoo Community Association (OCA)
Author-email: support@odoo-community.org
License: AGPL-3
Platform: UNKNOWN
Classifier: Programming Language :: Python
Classifier: Framework :: Odoo
Classifier: License :: OSI Approved :: GNU Affero General Public License v3
Requires-Python: ~=2.7
Requires-Dist: odoo (<9.0a,>=8.0a)
Requires-Dist: requests
